{
  "338723734263169025": {
    "username": "mystoq",
    "global_name": "silky",
    "avatar_url": "https://cdn.discordapp.com/avatars/338723734263169025/bb5e49991c710220f6c666b50c19981b.webp?size=256",
    "email": "harrisonjonathan05@gmail.com",
    "discord_id": "338723734263169025",
    "updated_at": 1775247389
  },
  "1097670742662979685": {
    "username": "walksey",
    "global_name": "Walksey",
    "avatar_url": "https://cdn.discordapp.com/avatars/1097670742662979685/190a9a9add7cbe20ebd3bfec24d68942.webp?size=256",
    "email": "scanatrum@gmail.com",
    "discord_id": "1097670742662979685",
    "updated_at": 1775248245
  }
}